bootstrap.py
buildout.cfg
setup.py
wasp/__init__.py
wasp/ftesting.zcml
wasp/interfaces.py
wasp/license.txt
wasp/readme.txt
wasp/status.py
wasp/tests.py
wasp/version.txt
wasp.egg-info/PKG-INFO
wasp.egg-info/SOURCES.txt
wasp.egg-info/dependency_links.txt
wasp.egg-info/not-zip-safe
wasp.egg-info/requires.txt
wasp.egg-info/top_level.txt
wasp/bulksms/__init__.py
wasp/bulksms/meta.zcml
wasp/bulksms/readme.txt
wasp/bulksms/tests.py
wasp/bulksms/zcml.py
wasp/demo/__init__.py
wasp/demo/meta.zcml
wasp/demo/readme.txt
wasp/demo/tests.py
wasp/demo/zcml.py