Metadata-Version: 1.0
Name: wasp
Version: 1.0.1
Summary: A library for abstracting interactions with different WASPs
Home-page: UNKNOWN
Author: Chris Withers
Author-email: chris@simplistix.co.uk
License: All rights reserved
Platform: UNKNOWN
